LICENSE
README.md
setup.py
examples/chopin2/chopin2.py
hdlib/__init__.py
hdlib/arithmetic.py
hdlib/space.py
hdlib/vector.py
hdlib.egg-info/PKG-INFO
hdlib.egg-info/SOURCES.txt
hdlib.egg-info/dependency_links.txt
hdlib.egg-info/not-zip-safe
hdlib.egg-info/requires.txt
hdlib.egg-info/top_level.txt
test/test.py