Metadata-Version: 2.4
Name: hdlib
Version: 2.0.0
Summary: Hyperdimensional Computing Library for building Vector Symbolic Architectures in Python
Home-page: http://github.com/cumbof/hdlib
Author: Fabio Cumbo
Author-email: fabio.cumbo@gmail.com
License: MIT
Project-URL: Issues, https://github.com/cumbof/hdlib/issues
Project-URL: Source, https://github.com/cumbof/hdlib
Project-URL: Wiki, https://github.com/cumbof/hdlib/wiki
Classifier: Intended Audience :: Developers
Classifier: Intended Audience :: Information Technology
Classifier: Intended Audience :: Science/Research
Classifier: License :: OSI Approved :: MIT License
Classifier: Programming Language :: Python :: 3
Classifier: Topic :: Scientific/Engineering
Requires-Python: >=3
License-File: LICENSE
Requires-Dist: numpy>=2.2.5
Requires-Dist: scikit-learn>=1.6.1
Requires-Dist: tabulate>=0.9.0
Dynamic: author
Dynamic: author-email
Dynamic: classifier
Dynamic: description
Dynamic: description-content-type
Dynamic: home-page
Dynamic: license
Dynamic: license-file
Dynamic: project-url
Dynamic: requires-dist
Dynamic: requires-python
Dynamic: summary
